sayou/document/__init__.py
sayou/document/models.py
sayou/document/pipeline.py
sayou/document/converter/image_converter.py
sayou/document/core/exceptions.py
sayou/document/interfaces/base_converter.py
sayou/document/interfaces/base_ocr.py
sayou/document/interfaces/base_parser.py
sayou/document/ocr/tesseract_ocr.py
sayou/document/parser/docx_parser.py
sayou/document/parser/excel_parser.py
sayou/document/parser/pdf_parser.py
sayou/document/parser/pptx_parser.py
sayou_document-0.3.2.dist-info/METADATA
sayou_document-0.3.2.dist-info/WHEEL
sayou_document-0.3.2.dist-info/RECORD
