Metadata-Version: 2.4
Name: sayou-document
Version: 0.3.2
Summary: Document components for the Sayou Data Platform
Project-URL: Homepage, https://www.sayouzone.com/
Project-URL: Documentation, https://sayouzone.github.io/sayou-fabric/
Project-URL: Repository, https://github.com/sayouzone/sayou-fabric
Author-email: Sayouzone <contact@sayouzone.com>
License:                                  Apache License
Classifier: License :: OSI Approved :: Apache Software License
Classifier: Operating System :: OS Independent
Classifier: Programming Language :: Python :: 3.9
Classifier: Programming Language :: Python :: 3.10
Classifier: Programming Language :: Python :: 3.11
Classifier: Topic :: Software Development :: Libraries :: Application Frameworks
Requires-Python: >=3.9
Requires-Dist: openpyxl==3.1.5
Requires-Dist: pillow>=10.0.0
Requires-Dist: pydantic~=2.12.4
Requires-Dist: pymupdf==1.25.5
Requires-Dist: python-docx==1.1.2
Requires-Dist: python-pptx==1.0.2
Requires-Dist: sayou-core~=0.3.0
Provides-Extra: all
Requires-Dist: pytesseract; extra == 'all'
Provides-Extra: ocr
Requires-Dist: pytesseract; extra == 'ocr'
